x_csfd_scraper/__init__.py
x_csfd_scraper/main.py
x_csfd_scraper/test.py
x_csfd_scraper/src/__init__.py
x_csfd_scraper/src/cli_objects.py
x_csfd_scraper/src/csfd_objects.py
x_csfd_scraper/src/csfd_parsers.py
x_csfd_scraper/src/csfd_scraper.py
x_csfd_scraper/src/csfd_utils.py
x_csfd_scraper-1.0.2.dist-info/LICENSE
x_csfd_scraper-1.0.2.dist-info/METADATA
x_csfd_scraper-1.0.2.dist-info/WHEEL
x_csfd_scraper-1.0.2.dist-info/entry_points.txt
x_csfd_scraper-1.0.2.dist-info/top_level.txt
x_csfd_scraper-1.0.2.dist-info/RECORD
