Metadata-Version: 2.1
Name: x-csfd-scraper
Version: 1.0.2
Summary: Simple scraper for CSFD.cz, a Czech movie database.
Home-page: https://github.com/TheNoiselessNoise/csfd_scraper
Author: XYZT
Author-email: xyzt@xyzt.cz
License: MIT
Classifier: Development Status :: 5 - Production/Stable
Classifier: Intended Audience :: Developers
Classifier: License :: OSI Approved :: MIT License
Classifier: Programming Language :: Python :: 3
License-File: LICENSE
Requires-Dist: beautifulsoup4 >=4.12.2
Requires-Dist: requests >=2.31.0
Requires-Dist: lxml >=4.9.2
